rapidchart_mcp/__init__.py
rapidchart_mcp/__main__.py
rapidchart_mcp/client.py
rapidchart_mcp/config.py
rapidchart_mcp/server.py
rapidchart_mcp/tools/__init__.py
rapidchart_mcp/tools/definitions.py
rapidchart_mcp/tools/executors.py
rapidchart_mcp-0.1.0.dist-info/LICENSE
rapidchart_mcp-0.1.0.dist-info/METADATA
rapidchart_mcp-0.1.0.dist-info/WHEEL
rapidchart_mcp-0.1.0.dist-info/entry_points.txt
rapidchart_mcp-0.1.0.dist-info/top_level.txt
rapidchart_mcp-0.1.0.dist-info/RECORD
