Metadata-Version: 2.1
Name: rapidchart-mcp
Version: 0.1.0
Summary: MCP server for RapidChart - Generate diagrams from code in Cursor
Author-email: RapidChart Team <hello@rapidchart.com>
Project-URL: Homepage, https://rapidchart.com
Project-URL: Repository, https://github.com/Samicostox/rapidchart-mcp
Project-URL: Documentation, https://docs.rapidchart.com/mcp
Classifier: Development Status :: 4 - Beta
Classifier: Intended Audience :: Developers
Classifier: License :: OSI Approved :: MIT License
Classifier: Programming Language :: Python :: 3
Classifier: Programming Language :: Python :: 3.10
Classifier: Programming Language :: Python :: 3.11
Classifier: Programming Language :: Python :: 3.12
Requires-Python: >=3.10
License-File: LICENSE
Requires-Dist: mcp>=0.9.0
Requires-Dist: httpx>=0.27.0
Requires-Dist: pydantic>=2.0.0
